flasko/__init__.py
flasko/app.py
flasko/json.py
flasko/auth/__init__.py
flasko/auth/auth_manager.py
flasko/auth/user_session.py
flasko/user/__init__.py
flasko/user/user.py
Flasko-0.1.0.dist-info/LICENSE
Flasko-0.1.0.dist-info/METADATA
Flasko-0.1.0.dist-info/WHEEL
Flasko-0.1.0.dist-info/top_level.txt
Flasko-0.1.0.dist-info/RECORD
