Metadata-Version: 2.1
Name: Flasko
Version: 0.1.0
Summary: A Flask Boilerplate
Home-page: https://github.com/fitiavana07/flasko
Author: Fitiavana Ramanandafy
Author-email: fitiavana.ramanandafy@gmail.com
License: MIT
Project-URL: Documentation, https://github.com/fitiavana07/flasko
Project-URL: Code, https://github.com/fitiavana07/flasko
Project-URL: Issue tracker, https://github.com/fitiavana07/flasko/issues
Platform: UNKNOWN
Classifier: Development Status :: 3 - Alpha
Classifier: Environment :: Web Environment
Classifier: Framework :: Flask
Classifier: Intended Audience :: Developers
Classifier: License :: OSI Approved :: MIT License
Classifier: Operating System :: OS Independent
Classifier: Programming Language :: Python :: 3.6
Classifier: Programming Language :: Python :: 3.7
Classifier: Programming Language :: Python :: 3.8
Classifier: Topic :: Internet :: WWW/HTTP :: WSGI :: Application
Classifier: Topic :: Software Development :: Libraries :: Python Modules
Requires-Python: >=3.6
Requires-Dist: Flask (>=1.1.1)
Requires-Dist: Flask-JSON (>=0.3.4)
Requires-Dist: Flask-Login (>=0.5.0)
Requires-Dist: flask-mongoengine (>=0.9.5)
Requires-Dist: mongoengine (>=0.19.1)
Provides-Extra: dev
Requires-Dist: pytest ; extra == 'dev'
Requires-Dist: pytest-sugar ; extra == 'dev'
Requires-Dist: mongomock ; extra == 'dev'
Requires-Dist: coverage ; extra == 'dev'
Requires-Dist: pre-commit ; extra == 'dev'
